{
  "doctors": [
    {
      "id": "1",
      "name": "Dr. Sarah Johnson",
      "email": "sarah.johnson@email.com",
      "password": "doctor123",
      "phone": "+1-555-0101",
      "specialty": "Cardiology",
      "qualifications": "MD, FACC",
      "experience": "15 years",
      "clinicAddress": "Heart Care Center, 123 Medical Plaza, New York",
      "clinicName": "Heart Care Center",
      "clinicPhone": "+1-555-0100",
      "clinicEmail": "info@heartcarecenter.com",
      "clinicTiming": "09:00 AM - 06:00 PM",
      "clinicClosed": "Sunday",
      "clinicLogo": "/logos/heart-care-center.svg",
      "clinicRegistration": "Reg. No: HC001234",
      "rating": 4.8,
      "reviewCount": 156,
      "consultationFee": 150,
      "videoConsultationFee": 100,
      "availability": {
        "clinic": [
          "Monday",
          "Wednesday",
          "Friday"
        ],
        "online": [
          "Tuesday",
          "Thursday",
          "Saturday"
        ]
      },
      "timeSlots": [
        "09:00",
        "10:00",
        "11:00",
        "14:00",
        "15:00",
        "16:00"
      ],
      "image": "/placeholder.svg?height=200&width=200",
      "about": "Experienced cardiologist specializing in heart disease prevention and treatment.",
      "consultationType": [
        "clinic",
        "video",
        "call"
      ]
    },
    {
      "id": "2",
      "name": "Dr. Michael Chen",
      "email": "michael.chen@email.com",
      "password": "doctor123",
      "phone": "+1-555-0102",
      "specialty": "Dermatology",
      "qualifications": "MD, FAAD",
      "experience": "12 years",
      "clinicAddress": "Skin Care Clinic, 456 Health Street, Los Angeles",
      "clinicName": "Skin Care Clinic",
      "clinicPhone": "+1-555-0200",
      "clinicEmail": "info@skincareclinic.com",
      "clinicTiming": "08:00 AM - 05:00 PM",
      "clinicClosed": "Saturday",
      "clinicLogo": "/logos/skin-care-clinic.svg",
      "clinicRegistration": "Reg. No: SC005678",
      "rating": 4.9,
      "reviewCount": 203,
      "consultationFee": 120,
      "videoConsultationFee": 80,
      "availability": {
        "clinic": [
          "Monday",
          "Tuesday",
          "Thursday"
        ],
        "online": [
          "Wednesday",
          "Friday",
          "Saturday"
        ]
      },
      "timeSlots": [
        "08:00",
        "09:00",
        "10:00",
        "13:00",
        "14:00",
        "15:00"
      ],
      "image": "/placeholder.svg?height=200&width=200",
      "about": "Board-certified dermatologist with expertise in skin conditions and cosmetic procedures.",
      "consultationType": [
        "clinic",
        "video",
        "call"
      ]
    },
    {
      "id": "3",
      "name": "Dr. Emily Rodriguez",
      "email": "emily.rodriguez@email.com",
      "password": "doctor123",
      "phone": "+1-555-0103",
      "specialty": "Neurology",
      "qualifications": "MD, PhD",
      "experience": "18 years",
      "clinicAddress": "Neuro Center, 789 Brain Avenue, Chicago",
      "clinicName": "Neuro Center",
      "clinicPhone": "+1-555-0300",
      "clinicEmail": "info@neurocenter.com",
      "clinicTiming": "08:00 AM - 07:00 PM",
      "clinicClosed": "Sunday",
      "clinicLogo": "/logos/neuro-center.svg",
      "clinicRegistration": "Reg. No: NC009012",
      "rating": 4.7,
      "reviewCount": 134,
      "consultationFee": 200,
      "videoConsultationFee": 150,
      "availability": {
        "clinic": [
          "Tuesday",
          "Wednesday",
          "Friday"
        ],
        "online": [
          "Monday",
          "Thursday",
          "Saturday"
        ]
      },
      "timeSlots": [
        "09:00",
        "10:00",
        "11:00",
        "14:00",
        "15:00"
      ],
      "image": "/placeholder.svg?height=200&width=200",
      "about": "Neurologist specializing in brain disorders and neurological conditions.",
      "consultationType": [
        "clinic",
        "video"
      ]
    },
    {
      "id": "4",
      "name": "Dr. James Wilson",
      "email": "james.wilson@email.com",
      "password": "doctor123",
      "phone": "+1-555-0104",
      "specialty": "Orthopedics",
      "qualifications": "MD, FAAOS",
      "experience": "20 years",
      "clinicAddress": "Bone & Joint Clinic, 321 Ortho Drive, Miami",
      "rating": 4.6,
      "reviewCount": 189,
      "consultationFee": 180,
      "videoConsultationFee": 120,
      "availability": {
        "clinic": [
          "Monday",
          "Wednesday",
          "Thursday"
        ],
        "online": [
          "Tuesday",
          "Friday",
          "Saturday"
        ]
      },
      "timeSlots": [
        "08:00",
        "09:00",
        "10:00",
        "13:00",
        "14:00"
      ],
      "image": "/placeholder.svg?height=200&width=200",
      "about": "Orthopedic surgeon specializing in joint replacement and sports medicine.",
      "consultationType": [
        "clinic",
        "video",
        "call"
      ]
    },
    {
      "id": "5",
      "name": "Dr. Lisa Thompson",
      "email": "lisa.thompson@email.com",
      "password": "doctor123",
      "phone": "+1-555-0105",
      "specialty": "Pediatrics",
      "qualifications": "MD, FAAP",
      "experience": "14 years",
      "clinicAddress": "Children's Health Center, 654 Kids Lane, Boston",
      "rating": 4.9,
      "reviewCount": 267,
      "consultationFee": 100,
      "videoConsultationFee": 70,
      "availability": {
        "clinic": [
          "Monday",
          "Tuesday",
          "Wednesday"
        ],
        "online": [
          "Thursday",
          "Friday",
          "Saturday"
        ]
      },
      "timeSlots": [
        "09:00",
        "10:00",
        "11:00",
        "14:00",
        "15:00",
        "16:00"
      ],
      "image": "/placeholder.svg?height=200&width=200",
      "about": "Pediatrician dedicated to providing comprehensive care for children and adolescents.",
      "consultationType": [
        "clinic",
        "video",
        "call"
      ]
    },
    {
      "id": "6",
      "name": "Dr. Robert Kim",
      "email": "robert.kim@email.com",
      "password": "doctor123",
      "phone": "+1-555-0106",
      "specialty": "Psychiatry",
      "qualifications": "MD, MRCPsych",
      "experience": "16 years",
      "clinicAddress": "Mental Health Center, 987 Wellness Blvd, Seattle",
      "rating": 4.8,
      "reviewCount": 145,
      "consultationFee": 160,
      "videoConsultationFee": 120,
      "availability": {
        "clinic": [
          "Tuesday",
          "Thursday",
          "Friday"
        ],
        "online": [
          "Monday",
          "Wednesday",
          "Saturday"
        ]
      },
      "timeSlots": [
        "10:00",
        "11:00",
        "14:00",
        "15:00",
        "16:00"
      ],
      "image": "/placeholder.svg?height=200&width=200",
      "about": "Psychiatrist specializing in mental health disorders and therapy.",
      "consultationType": [
        "clinic",
        "video",
        "call"
      ]
    },
    {
      "id": "7",
      "name": "Dr. Amanda Davis",
      "email": "amanda.davis@email.com",
      "password": "doctor123",
      "phone": "+1-555-0107",
      "specialty": "General Medicine",
      "qualifications": "MD, ABIM",
      "experience": "10 years",
      "clinicAddress": "Family Health Clinic, 147 Main Street, Denver",
      "rating": 4.7,
      "reviewCount": 198,
      "consultationFee": 90,
      "videoConsultationFee": 60,
      "availability": {
        "clinic": [
          "Monday",
          "Wednesday",
          "Friday"
        ],
        "online": [
          "Tuesday",
          "Thursday",
          "Saturday"
        ]
      },
      "timeSlots": [
        "08:00",
        "09:00",
        "10:00",
        "13:00",
        "14:00",
        "15:00"
      ],
      "image": "/placeholder.svg?height=200&width=200",
      "about": "General practitioner providing comprehensive primary care services.",
      "consultationType": [
        "clinic",
        "video",
        "call"
      ]
    }
  ],
  "patients": [
    {
      "id": "1",
      "name": "John Doe",
      "email": "john@example.com",
      "password": "patient123",
      "phone": "+1-555-1001"
    },
    {
      "id": "1754907017804",
      "name": "David Lee",
      "email": "david@email.com",
      "phone": "(555) 555-3456",
      "password": "patient123",
      "specialty": "",
      "qualifications": "",
      "experience": "",
      "clinicAddress": ""
    },
    {
      "id": "1754912750543",
      "name": "Alice Bloom",
      "email": "alice@email.com",
      "phone": "7896333333",
      "password": "alice123",
      "specialty": "",
      "qualifications": "",
      "experience": "",
      "clinicAddress": ""
    }
  ],
  "appointments": [
    {
      "id": "1753449750705",
      "doctorId": "1",
      "patientId": "1",
      "doctorName": "Dr. Sarah Johnson",
      "patientName": "John Doe",
      "specialty": "Cardiology",
      "date": "2025-08-12",
      "time": "09:02",
      "status": "rescheduled",
      "consultationType": "video",
      "symptoms": "hshshs",
      "fee": 100
    },
    {
      "id": "1753608241357",
      "doctorId": "1",
      "patientId": "1",
      "doctorName": "Dr. Sarah Johnson",
      "patientName": "John Doe",
      "specialty": "Cardiology",
      "date": "2025-07-27",
      "time": "10:00",
      "status": "cancelled"
    },
    {
      "id": "1753608244069",
      "doctorId": "2",
      "patientId": "1",
      "doctorName": "Dr. Michael Chen",
      "patientName": "John Doe",
      "specialty": "Dermatology",
      "date": "2025-07-27",
      "time": "10:00",
      "status": "pending"
    },
    {
      "id": "1753608246626",
      "doctorId": "5",
      "patientId": "1",
      "doctorName": "Dr. Lisa Thompson",
      "patientName": "John Doe",
      "specialty": "Pediatrics",
      "date": "2025-07-27",
      "time": "10:00",
      "status": "pending"
    },
    {
      "id": "1753608486759",
      "doctorId": "7",
      "patientId": "1",
      "doctorName": "Dr. Amanda Davis",
      "patientName": "John Doe",
      "specialty": "General Medicine",
      "date": "2025-07-27",
      "time": "10:00",
      "status": "pending"
    },
    {
      "id": "1753608594110",
      "doctorId": "1",
      "patientId": "1",
      "doctorName": "Dr. Sarah Johnson",
      "patientName": "John Doe",
      "specialty": "Cardiology",
      "date": "2025-07-27",
      "time": "10:00",
      "status": "completed",
      "prescription": {
        "medicationName": "Syrup",
        "dosage": "10ml",
        "frequency": "Twice Daily",
        "instructions": "Take Rest",
        "appointmentId": "1753608594110",
        "id": "5e664983-838a-421f-bea9-5ef07d4c2ce0",
        "createdAt": "2025-08-06T16:25:40.887Z"
      }
    },
    {
      "id": "1753608818624",
      "doctorId": "1",
      "patientId": "1",
      "doctorName": "Dr. Sarah Johnson",
      "patientName": "John Doe",
      "specialty": "Cardiology",
      "date": "2025-07-27",
      "time": "10:00",
      "status": "cancelled"
    },
    {
      "id": "1753609062114",
      "doctorId": "1",
      "patientId": "1",
      "doctorName": "Dr. Sarah Johnson",
      "patientName": "John Doe",
      "specialty": "Cardiology",
      "date": "2025-07-27",
      "time": "10:00",
      "status": "pending"
    },
    {
      "id": "1753969192000",
      "doctorId": "2",
      "patientId": "1",
      "doctorName": "Dr. Michael Chen",
      "patientName": "John Doe",
      "specialty": "Dermatology",
      "date": "2025-08-04",
      "time": "14:00",
      "status": "confirmed",
      "consultationType": "clinic",
      "symptoms": "",
      "fee": 120
    },
    {
      "id": "1753970290676",
      "doctorId": "1",
      "patientId": "1",
      "doctorName": "Dr. Sarah Johnson",
      "patientName": "John Doe",
      "specialty": "Cardiology",
      "date": "2025-08-12",
      "time": "07:02",
      "status": "completed",
      "consultationType": "clinic",
      "symptoms": "",
      "fee": 150
    },
    {
      "id": "1753971379501",
      "doctorId": "1",
      "patientId": "1",
      "doctorName": "Dr. Sarah Johnson",
      "patientName": "John Doe",
      "specialty": "Cardiology",
      "date": "2025-08-10",
      "time": "12:02",
      "status": "completed",
      "consultationType": "clinic",
      "symptoms": "",
      "fee": 150,
      "prescription": {
        "medicationName": "Crocin",
        "dosage": "200mg",
        "frequency": "Daily",
        "instructions": "Take Rest",
        "appointmentId": "1753971379501",
        "id": "5f859b2d-dbaa-4f1b-8d6a-0e6f88594767",
        "createdAt": "2025-08-06T16:39:40.058Z"
      }
    },
    {
      "id": "1753971844236",
      "doctorId": "1",
      "patientId": "1",
      "doctorName": "Dr. Sarah Johnson",
      "patientName": "John Doe",
      "specialty": "Cardiology",
      "date": "2025-08-08",
      "time": "16:00",
      "status": "completed",
      "consultationType": "clinic",
      "symptoms": "",
      "fee": 150,
      "prescription": {
        "medicationName": "Crocin",
        "dosage": "200mg",
        "frequency": "daily",
        "instructions": "",
        "appointmentId": "1753971844236",
        "id": "e30f717c-8197-45cd-a002-d7e9f8f1275b",
        "createdAt": "2025-08-06T16:12:40.691Z"
      }
    },
    {
      "id": "1753671149792",
      "doctorId": "4",
      "patientId": "1",
      "doctorName": "Dr. James Wilson",
      "patientName": "John Doe",
      "specialty": "Orthopedics",
      "date": "2025-07-30",
      "time": "09:00",
      "status": "confirmed",
      "consultationType": "clinic",
      "symptoms": "",
      "fee": 180
    },
    {
      "id": "1753780484677",
      "doctorId": "2",
      "patientId": "1",
      "doctorName": "Dr. Michael Chen",
      "patientName": "John Doe",
      "specialty": "Dermatology",
      "date": "2025-07-31",
      "time": "09:00",
      "status": "confirmed",
      "consultationType": "clinic",
      "symptoms": "",
      "fee": 120
    },
    {
      "id": "1754312327084",
      "doctorId": "1",
      "patientId": "1",
      "doctorName": "Dr. Sarah Johnson",
      "patientName": "John Doe",
      "specialty": "Cardiology",
      "date": "2025-08-09",
      "time": "14:00",
      "status": "completed",
      "consultationType": "clinic",
      "symptoms": "",
      "fee": 150
    },
    {
      "id": "1754593270327",
      "doctorId": "1",
      "patientId": "1",
      "doctorName": "Dr. Sarah Johnson",
      "patientName": "John Doe",
      "specialty": "Cardiology",
      "date": "2025-08-07",
      "time": "10:00",
      "status": "confirmed",
      "consultationType": "clinic",
      "symptoms": "",
      "fee": 150
    },
    {
      "id": "1754594159646",
      "doctorId": "1",
      "patientId": "1",
      "doctorName": "Dr. Sarah Johnson",
      "patientName": "John Doe",
      "specialty": "Cardiology",
      "date": "2025-08-10",
      "time": "14:00",
      "status": "rescheduled",
      "consultationType": "clinic",
      "symptoms": "",
      "fee": 150
    },
    {
      "id": "1754594282873",
      "doctorId": "1",
      "patientId": "1",
      "doctorName": "Dr. Sarah Johnson",
      "patientName": "John Doe",
      "specialty": "Cardiology",
      "date": "2025-08-10",
      "time": "11:00",
      "status": "completed",
      "consultationType": "clinic",
      "symptoms": "",
      "fee": 150
    },
    {
      "id": "1754629124588",
      "doctorId": "1",
      "patientId": "1",
      "doctorName": "Dr. Sarah Johnson",
      "patientName": "John Doe",
      "specialty": "Cardiology",
      "date": "2025-08-13",
      "time": "11:00",
      "status": "completed",
      "consultationType": "clinic",
      "symptoms": "",
      "fee": 150
    },
    {
      "id": "1754907081580",
      "doctorId": "1",
      "patientId": "1754907017804",
      "doctorName": "Dr. Sarah Johnson",
      "patientName": "David Lee",
      "specialty": "Cardiology",
      "date": "2025-08-13",
      "time": "11:00",
      "status": "completed",
      "consultationType": "clinic",
      "symptoms": "",
      "fee": 150
    },
    {
      "id": "1754912869624",
      "doctorId": "1",
      "patientId": "1754912750543",
      "doctorName": "Dr. Sarah Johnson",
      "patientName": "Alice Bloom",
      "specialty": "Cardiology",
      "date": "2025-08-15",
      "time": "11:00",
      "status": "confirmed",
      "consultationType": "clinic",
      "symptoms": "",
      "fee": 150
    },
    {
      "id": "1755008195658",
      "doctorId": "1",
      "patientId": "1",
      "doctorName": "Dr. Sarah Johnson",
      "patientName": "John Doe",
      "specialty": "Cardiology",
      "date": "2025-05-25",
      "time": "16:00",
      "status": "confirmed",
      "consultationType": "clinic",
      "symptoms": "",
      "fee": 150
    },
    {
      "id": "1755008340281",
      "doctorId": "1",
      "patientId": "1",
      "doctorName": "Dr. Sarah Johnson",
      "patientName": "John Doe",
      "specialty": "Cardiology",
      "date": "2025-02-22",
      "time": "10:00",
      "status": "cancelled",
      "consultationType": "clinic",
      "symptoms": "",
      "fee": 150
    },
    {
      "id": "1755008393562",
      "doctorId": "1",
      "patientId": "1",
      "doctorName": "Dr. Sarah Johnson",
      "patientName": "John Doe",
      "specialty": "Cardiology",
      "date": "2024-10-20",
      "time": "16:00",
      "status": "completed",
      "consultationType": "clinic",
      "symptoms": "",
      "fee": 150
    }
  ],
  "diagnoses": [
    {
      "id": "diag1",
      "appointmentId": "1754629124588",
      "patientId": "1",
      "doctorId": "1",
      "patientName": "John Doe",
      "doctorName": "Dr. Sarah Johnson",
      "specialty": "General Medicine",
      "description": "Patient presented with symptoms of a common cold. Advised rest and fluids.",
      "notes": "No fever, minor congestion. Recommended over-the-counter remedies.",
      "createdAt": "2023-08-13T12:00:00Z"
    }
  ],
  "prescriptions": [
    {
      "id": "1",
      "appointmentId": "1753969192000",
      "patientId": "1",
      "doctorId": "2",
      "patientName": "John Doe",
      "doctorName": "Dr. Michael Chen",
      "specialty": "Dermatology",
      "diagnosis": "Acne vulgaris",
      "medications": [
        {
          "id": "med1",
          "name": "Benzoyl Peroxide 5%",
          "dosage": "Apply twice daily",
          "frequency": "Morning and evening",
          "duration": "4 weeks",
          "instructions": "Apply to affected areas after washing face"
        },
        {
          "id": "med2",
          "name": "Clindamycin 1%",
          "dosage": "Apply once daily",
          "frequency": "Evening only",
          "duration": "4 weeks",
          "instructions": "Apply after benzoyl peroxide"
        }
      ],
      "lifestyleRecommendations": [
        "Wash face twice daily with gentle cleanser",
        "Avoid touching face with dirty hands",
        "Use oil-free sunscreen"
      ],
      "followUpDate": "2025-09-04",
      "createdAt": "2025-08-04T10:00:00Z",
      "status": "active"
    },
    {
      "id": "2",
      "appointmentId": "1753671149792",
      "patientId": "1",
      "doctorId": "4",
      "patientName": "John Doe",
      "doctorName": "Dr. James Wilson",
      "specialty": "Orthopedics",
      "diagnosis": "Knee pain - suspected ligament strain",
      "medications": [
        {
          "id": "med3",
          "name": "Ibuprofen 400mg",
          "dosage": "1 tablet",
          "frequency": "Every 6 hours as needed",
          "duration": "7 days",
          "instructions": "Take with food to avoid stomach upset"
        }
      ],
      "lifestyleRecommendations": [
        "Rest the affected knee",
        "Apply ice pack for 20 minutes every 4 hours",
        "Elevate leg when sitting",
        "Avoid strenuous activities for 2 weeks"
      ],
      "followUpDate": "2025-08-30",
      "createdAt": "2025-07-30T09:00:00Z",
      "status": "active"
    },
    {
      "id": "1754591116383",
      "appointmentId": "1754312327084",
      "patientId": "1",
      "doctorId": "1",
      "patientName": "John Doe",
      "doctorName": "Dr. Sarah Johnson",
      "specialty": "Cardiology",
      "diagnosis": "Knee pain - suspected ligament strain",
      "medications": [
        {
          "id": "1",
          "name": "Ibuprofen 400mg",
          "dosage": "2",
          "frequency": "2",
          "duration": "5",
          "instructions": "take bed rest for 5 days"
        }
      ],
      "lifestyleRecommendations": [
        "dont apply force on the knee"
      ],
      "followUpDate": "2025-08-13",
      "status": "active",
      "createdAt": "2025-08-07T18:25:16.383Z"
    },
    {
      "id": "1754591878606",
      "appointmentId": "1753608594110",
      "patientId": "1",
      "doctorId": "1",
      "patientName": "John Doe",
      "doctorName": "Dr. Sarah Johnson",
      "specialty": "Cardiology",
      "diagnosis": "Fever",
      "medications": [
        {
          "id": "1",
          "name": "Dolo",
          "dosage": "200mg",
          "frequency": "3 times",
          "duration": "3 days",
          "instructions": "rest"
        }
      ],
      "lifestyleRecommendations": [
        "rest"
      ],
      "followUpDate": "2025-08-13",
      "status": "active",
      "createdAt": "2025-08-07T18:37:58.606Z"
    },
    {
      "id": "1754592822711",
      "appointmentId": "1753970290676",
      "patientId": "1",
      "doctorId": "1",
      "patientName": "John Doe",
      "doctorName": "Dr. Sarah Johnson",
      "specialty": "Cardiology",
      "diagnosis": "Migraine",
      "medications": [
        {
          "id": "1",
          "name": "Saridon",
          "dosage": "20mg",
          "frequency": "Twice Daily",
          "duration": "10 days",
          "instructions": "rest"
        }
      ],
      "lifestyleRecommendations": [
        "dont use phone too much"
      ],
      "followUpDate": "2025-08-09",
      "status": "active",
      "createdAt": "2025-08-07T18:53:42.711Z"
    },
    {
      "id": "1754593964055",
      "appointmentId": "1753608594110",
      "patientId": "1",
      "doctorId": "1",
      "patientName": "John Doe",
      "doctorName": "Dr. Sarah Johnson",
      "specialty": "Cardiology",
      "diagnosis": "Cough & Cold",
      "medications": [
        {
          "id": "1",
          "name": "Tonic",
          "dosage": "100ml",
          "frequency": "Twice",
          "duration": "30 days",
          "instructions": "warm place "
        }
      ],
      "lifestyleRecommendations": [
        "take breath"
      ],
      "followUpDate": "2025-08-15",
      "status": "active",
      "createdAt": "2025-08-07T19:12:44.055Z"
    },
    {
      "id": "1754594390208",
      "appointmentId": "1754594282873",
      "patientId": "1",
      "doctorId": "1",
      "patientName": "John Doe",
      "doctorName": "Dr. Sarah Johnson",
      "specialty": "Cardiology",
      "diagnosis": "Leg fracture",
      "medications": [
        {
          "id": "1",
          "name": "ibuforem 100mg",
          "dosage": "50mg",
          "frequency": "Once daily",
          "duration": "4 days",
          "instructions": "take bed rest"
        }
      ],
      "lifestyleRecommendations": [
        "dont force on legs"
      ],
      "followUpDate": "2025-08-20",
      "status": "active",
      "createdAt": "2025-08-07T19:19:50.208Z"
    },
    {
      "id": "1754629863656",
      "appointmentId": "1754629124588",
      "patientId": "1",
      "doctorId": "1",
      "patientName": "John Doe",
      "doctorName": "Dr. Sarah Johnson",
      "specialty": "Cardiology",
      "diagnosis": "Shoulder pain",
      "medications": [
        {
          "id": "1",
          "name": "Naproxen",
          "dosage": "10mg",
          "frequency": "2 times",
          "duration": "5 days",
          "instructions": "Take Bed Rest "
        }
      ],
      "lifestyleRecommendations": [
        "take bed rest"
      ],
      "followUpDate": "2025-08-14",
      "status": "active",
      "createdAt": "2025-08-08T05:11:03.656Z"
    },
    {
      "id": "1754907418996",
      "appointmentId": "1754907081580",
      "patientId": "1754907017804",
      "doctorId": "1",
      "patientName": "David Lee",
      "doctorName": "Dr. Sarah Johnson",
      "specialty": "Cardiology",
      "diagnosis": "Hypertension (High Blood Pressure)",
      "medications": [
        {
          "id": "1",
          "name": "Lisinopril 10mg",
          "dosage": "1 tablet",
          "frequency": "Once daily",
          "duration": "30 days",
          "instructions": "Take in the morning with a glass of water. Do not stop taking abruptly."
        },
        {
          "id": "1754907313511",
          "name": "Aspirin 81mg",
          "dosage": "1 tablet",
          "frequency": "Once daily",
          "duration": "Ongoing",
          "instructions": "Take at the same time each day, preferably with a meal."
        }
      ],
      "lifestyleRecommendations": [
        "Monitor blood pressure daily using a home monitor"
      ],
      "followUpDate": "2025-09-13",
      "status": "active",
      "createdAt": "2025-08-11T10:16:58.996Z"
    }
  ]
}